_foo.cpython-39-x86_64-linux-gnu.so
tensorflow_recommenders_addons/conftest.py
tensorflow_recommenders_addons/register.py
tensorflow_recommenders_addons/__init__.py
tensorflow_recommenders_addons/version.py
tensorflow_recommenders_addons/tests/__init__.py
tensorflow_recommenders_addons/utils/test_utils.py
tensorflow_recommenders_addons/utils/resource_loader.py
tensorflow_recommenders_addons/utils/check_platform.py
tensorflow_recommenders_addons/utils/types.py
tensorflow_recommenders_addons/utils/__init__.py
tensorflow_recommenders_addons/utils/ensure_tf_install.py
tensorflow_recommenders_addons/dynamic_embedding/__init__.py
tensorflow_recommenders_addons/dynamic_embedding/core/_redis_table_ops.so
tensorflow_recommenders_addons/dynamic_embedding/core/_math_ops.so
tensorflow_recommenders_addons/dynamic_embedding/core/_cuckoo_hashtable_ops.so
tensorflow_recommenders_addons/dynamic_embedding/core/_data_flow_ops.so
tensorflow_recommenders_addons/dynamic_embedding/python/__init__.py
tensorflow_recommenders_addons/dynamic_embedding/python/ops/dynamic_embedding_ops.py
tensorflow_recommenders_addons/dynamic_embedding/python/ops/math_grad.py
tensorflow_recommenders_addons/dynamic_embedding/python/ops/cuckoo_hashtable_ops.py
tensorflow_recommenders_addons/dynamic_embedding/python/ops/dynamic_embedding_variable.py
tensorflow_recommenders_addons/dynamic_embedding/python/ops/tf_save_restore_patch.py
tensorflow_recommenders_addons/dynamic_embedding/python/ops/math_ops.py
tensorflow_recommenders_addons/dynamic_embedding/python/ops/restrict_policies.py
tensorflow_recommenders_addons/dynamic_embedding/python/ops/embedding_weights.py
tensorflow_recommenders_addons/dynamic_embedding/python/ops/data_flow_ops.py
tensorflow_recommenders_addons/dynamic_embedding/python/ops/__init__.py
tensorflow_recommenders_addons/dynamic_embedding/python/ops/distributed_embedding_variable.py
tensorflow_recommenders_addons_beta-0.8.1.dev1.dist-info/LICENSE
tensorflow_recommenders_addons_beta-0.8.1.dev1.dist-info/RECORD
tensorflow_recommenders_addons_beta-0.8.1.dev1.dist-info/WHEEL
tensorflow_recommenders_addons_beta-0.8.1.dev1.dist-info/top_level.txt
tensorflow_recommenders_addons_beta-0.8.1.dev1.dist-info/METADATA
